 [
  {
    "id":1,
    "title":"Attract More Attention Sales And Profits",
    "department":"Marketing",
     "duration":"Jun 15,2022",
     "pic":"/blog-01.jpg"
  },
  {
    "id":2,
    "title":"11 Tips To Help You Get New Clints",
    "department":"Sales Order",
     "duration":"May 20,2022",
     "pic":"/blog-02.jpg"
  },
  {
    "id":3,
    "title":"An Overworked Best Newspaper Editor",
    "department":"Design",
     "duration":"May 25,2022",
     "pic":"/blog-03.jpg"
  },
  {

    "id":4,
    "title":"A Solution Build for Developer Teachers",
    "department":"Seo",
     "duration":"Jul 15,2022",
     "pic":"/blog-04.jpg"
  },
  {
    "id":5,
    "title":"Attract More Attention Sales And Profits",
    "department":"Marketing",
     "duration":"Jun 15,2022",
     "pic":"/blog-01.jpg"
  },
  {
    "id":6,
    "title":"11 Tips To Help You Get New Clints",
    "department":"Sales Order",
     "duration":"May 20,2022",
     "pic":"/blog-02.jpg"
  },
  {
    "id":7,
    "title":"An Overworked Best Newspaper Editor",
    "department":"Design",
     "duration":"May 25,2022",
     "pic":"/blog-03.jpg"
  },
  {

    "id":8,
    "title":"A Solution Build for Developer Teachers",
    "department":"Seo",
     "duration":"Jul 15,2022",
     "pic":"/blog-04.jpg"
  },
  {
    "id":9,
    "title":"Attract More Attention Sales And Profits",
    "department":"Marketing",
     "duration":"Jun 15,2022",
     "pic":"/blog-01.jpg"
  },
  {
    "id":10,
    "title":"11 Tips To Help You Get New Clints",
    "department":"Sales Order",
     "duration":"May 20,2022",
     "pic":"/blog-02.jpg"
  },
  {
    "id":11,
    "title":"An Overworked Best Newspaper Editor",
    "department":"Design",
     "duration":"May 25,2022",
     "pic":"/blog-03.jpg"
  },
  {

    "id":12,
    "title":"A Solution Build for  Developer Teachers",
    "department":"Seo",
     "duration":"Jul 15,2022",
     "pic":"/blog-04.jpg"
  }

]
